{
  "kind": "DeploymentList",
  "apiVersion": "apps/v1",
  "metadata": {
    "resourceVersion": "8767"
  },
  "items": [
    {
      "kind": "Deployment",
      "apiVersion": "apps/v1",
      "metadata": {
        "name": "local-path-provisioner",
        "namespace": "local-path-storage",
        "uid": "5eaa1863-f152-4a87-9a70-26b85ae05b46",
        "resourceVersion": "491",
        "generation": 1,
        "creationTimestamp": "2025-08-09T22:55:06Z",
        "annotations": {
          "deployment.kubernetes.io/revision": "1",
          "kubectl.kubernetes.io/last-applied-configuration": "{\"apiVersion\":\"apps/v1\",\"kind\":\"Deployment\",\"metadata\":{\"annotations\":{},\"name\":\"local-path-provisioner\",\"namespace\":\"local-path-storage\"},\"spec\":{\"replicas\":1,\"selector\":{\"matchLabels\":{\"app\":\"local-path-provisioner\"}},\"template\":{\"metadata\":{\"labels\":{\"app\":\"local-path-provisioner\"}},\"spec\":{\"containers\":[{\"command\":[\"local-path-provisioner\",\"--debug\",\"start\",\"--helper-image\",\"docker.io/kindest/local-path-helper:v20241212-8ac705d0\",\"--config\",\"/etc/config/config.json\"],\"env\":[{\"name\":\"POD_NAMESPACE\",\"valueFrom\":{\"fieldRef\":{\"fieldPath\":\"metadata.namespace\"}}},{\"name\":\"CONFIG_MOUNT_PATH\",\"value\":\"/etc/config/\"}],\"image\":\"docker.io/kindest/local-path-provisioner:v20250214-acbabc1a\",\"imagePullPolicy\":\"IfNotPresent\",\"name\":\"local-path-provisioner\",\"volumeMounts\":[{\"mountPath\":\"/etc/config/\",\"name\":\"config-volume\"}]}],\"nodeSelector\":{\"kubernetes.io/os\":\"linux\"},\"serviceAccountName\":\"local-path-provisioner-service-account\",\"tolerations\":[{\"effect\":\"NoSchedule\",\"key\":\"node-role.kubernetes.io/control-plane\",\"operator\":\"Equal\"},{\"effect\":\"NoSchedule\",\"key\":\"node-role.kubernetes.io/master\",\"operator\":\"Equal\"}],\"volumes\":[{\"configMap\":{\"name\":\"local-path-config\"},\"name\":\"config-volume\"}]}}}}\n"
        },
        "managedFields": [
          {
            "manager": "kubectl-client-side-apply",
            "operation": "Update",
            "apiVersion": "apps/v1",
            "time": "2025-08-09T22:55:06Z",
            "fieldsType": "FieldsV1",
            "fieldsV1": {
              "f:metadata": {
                "f:annotations": {
                  ".": {},
                  "f:kubectl.kubernetes.io/last-applied-configuration": {}
                }
              },
              "f:spec": {
                "f:progressDeadlineSeconds": {},
                "f:replicas": {},
                "f:revisionHistoryLimit": {},
                "f:selector": {},
                "f:strategy": {
                  "f:rollingUpdate": {
                    ".": {},
                    "f:maxSurge": {},
                    "f:maxUnavailable": {}
                  },
                  "f:type": {}
                },
                "f:template": {
                  "f:metadata": {
                    "f:labels": {
                      ".": {},
                      "f:app": {}
                    }
                  },
                  "f:spec": {
                    "f:containers": {
                      "k:{\"name\":\"local-path-provisioner\"}": {
                        ".": {},
                        "f:command": {},
                        "f:env": {
                          ".": {},
                          "k:{\"name\":\"CONFIG_MOUNT_PATH\"}": {
                            ".": {},
                            "f:name": {},
                            "f:value": {}
                          },
                          "k:{\"name\":\"POD_NAMESPACE\"}": {
                            ".": {},
                            "f:name": {},
                            "f:valueFrom": {
                              ".": {},
                              "f:fieldRef": {}
                            }
                          }
                        },
                        "f:image": {},
                        "f:imagePullPolicy": {},
                        "f:name": {},
                        "f:resources": {},
                        "f:terminationMessagePath": {},
                        "f:terminationMessagePolicy": {},
                        "f:volumeMounts": {
                          ".": {},
                          "k:{\"mountPath\":\"/etc/config/\"}": {
                            ".": {},
                            "f:mountPath": {},
                            "f:name": {}
                          }
                        }
                      }
                    },
                    "f:dnsPolicy": {},
                    "f:nodeSelector": {},
                    "f:restartPolicy": {},
                    "f:schedulerName": {},
                    "f:securityContext": {},
                    "f:serviceAccount": {},
                    "f:serviceAccountName": {},
                    "f:terminationGracePeriodSeconds": {},
                    "f:tolerations": {},
                    "f:volumes": {
                      ".": {},
                      "k:{\"name\":\"config-volume\"}": {
                        ".": {},
                        "f:configMap": {
                          ".": {},
                          "f:defaultMode": {},
                          "f:name": {}
                        },
                        "f:name": {}
                      }
                    }
                  }
                }
              }
            }
          },
          {
            "manager": "kube-controller-manager",
            "operation": "Update",
            "apiVersion": "apps/v1",
            "time": "2025-08-09T22:55:25Z",
            "fieldsType": "FieldsV1",
            "fieldsV1": {
              "f:metadata": {
                "f:annotations": {
                  "f:deployment.kubernetes.io/revision": {}
                }
              },
              "f:status": {
                "f:availableReplicas": {},
                "f:conditions": {
                  ".": {},
                  "k:{\"type\":\"Available\"}": {
                    ".": {},
                    "f:lastTransitionTime": {},
                    "f:lastUpdateTime": {},
                    "f:message": {},
                    "f:reason": {},
                    "f:status": {},
                    "f:type": {}
                  },
                  "k:{\"type\":\"Progressing\"}": {
                    ".": {},
                    "f:lastTransitionTime": {},
                    "f:lastUpdateTime": {},
                    "f:message": {},
                    "f:reason": {},
                    "f:status": {},
                    "f:type": {}
                  }
                },
                "f:observedGeneration": {},
                "f:readyReplicas": {},
                "f:replicas": {},
                "f:updatedReplicas": {}
              }
            },
            "subresource": "status"
          }
        ]
      },
      "spec": {
        "replicas": 1,
        "selector": {
          "matchLabels": {
            "app": "local-path-provisioner"
          }
        },
        "template": {
          "metadata": {
            "creationTimestamp": null,
            "labels": {
              "app": "local-path-provisioner"
            }
          },
          "spec": {
            "volumes": [
              {
                "name": "config-volume",
                "configMap": {
                  "name": "local-path-config",
                  "defaultMode": 420
                }
              }
            ],
            "containers": [
              {
                "name": "local-path-provisioner",
                "image": "docker.io/kindest/local-path-provisioner:v20250214-acbabc1a",
                "command": [
                  "local-path-provisioner",
                  "--debug",
                  "start",
                  "--helper-image",
                  "docker.io/kindest/local-path-helper:v20241212-8ac705d0",
                  "--config",
                  "/etc/config/config.json"
                ],
                "env": [
                  {
                    "name": "POD_NAMESPACE",
                    "valueFrom": {
                      "fieldRef": {
                        "apiVersion": "v1",
                        "fieldPath": "metadata.namespace"
                      }
                    }
                  },
                  {
                    "name": "CONFIG_MOUNT_PATH",
                    "value": "/etc/config/"
                  }
                ],
                "resources": {},
                "volumeMounts": [
                  {
                    "name": "config-volume",
                    "mountPath": "/etc/config/"
                  }
                ],
                "terminationMessagePath": "/dev/termination-log",
                "terminationMessagePolicy": "File",
                "imagePullPolicy": "IfNotPresent"
              }
            ],
            "restartPolicy": "Always",
            "terminationGracePeriodSeconds": 30,
            "dnsPolicy": "ClusterFirst",
            "nodeSelector": {
              "kubernetes.io/os": "linux"
            },
            "serviceAccountName": "local-path-provisioner-service-account",
            "serviceAccount": "local-path-provisioner-service-account",
            "securityContext": {},
            "schedulerName": "default-scheduler",
            "tolerations": [
              {
                "key": "node-role.kubernetes.io/control-plane",
                "operator": "Equal",
                "effect": "NoSchedule"
              },
              {
                "key": "node-role.kubernetes.io/master",
                "operator": "Equal",
                "effect": "NoSchedule"
              }
            ]
          }
        },
        "strategy": {
          "type": "RollingUpdate",
          "rollingUpdate": {
            "maxUnavailable": "25%",
            "maxSurge": "25%"
          }
        },
        "revisionHistoryLimit": 10,
        "progressDeadlineSeconds": 600
      },
      "status": {
        "observedGeneration": 1,
        "replicas": 1,
        "updatedReplicas": 1,
        "readyReplicas": 1,
        "availableReplicas": 1,
        "conditions": [
          {
            "type": "Available",
            "status": "True",
            "lastUpdateTime": "2025-08-09T22:55:25Z",
            "lastTransitionTime": "2025-08-09T22:55:25Z",
            "reason": "MinimumReplicasAvailable",
            "message": "Deployment has minimum availability."
          },
          {
            "type": "Progressing",
            "status": "True",
            "lastUpdateTime": "2025-08-09T22:55:25Z",
            "lastTransitionTime": "2025-08-09T22:55:11Z",
            "reason": "NewReplicaSetAvailable",
            "message": "ReplicaSet \"local-path-provisioner-7dc846544d\" has successfully progressed."
          }
        ]
      }
    }
  ]
}
